ChatGPT/__init__.py
AI_ChatGPT_Free-2024.8.22.dist-info/LICENSE
AI_ChatGPT_Free-2024.8.22.dist-info/METADATA
AI_ChatGPT_Free-2024.8.22.dist-info/WHEEL
AI_ChatGPT_Free-2024.8.22.dist-info/top_level.txt
AI_ChatGPT_Free-2024.8.22.dist-info/RECORD
