Metadata-Version: 2.1
Name: AI-ChatGPT-Free
Version: 2024.8.22
Summary: 免费的ChatGPT Python库
Home-page: https://github.com/longliangzhe/ChatGpt-free
Author: 龙亮哲
Author-email: 17818883308@139.com
Platform: Windows
Platform: Linux
Classifier: Programming Language :: Python :: 3
Classifier: License :: OSI Approved :: MIT License
Classifier: Operating System :: OS Independent
Requires-Python: >=3
License-File: LICENSE
